opengreywolfoptimizer/__init__.py
opengreywolfoptimizer/optimizer.py
opengreywolfoptimizer-0.1.0.dist-info/METADATA
opengreywolfoptimizer-0.1.0.dist-info/WHEEL
opengreywolfoptimizer-0.1.0.dist-info/top_level.txt
opengreywolfoptimizer-0.1.0.dist-info/RECORD
