Metadata-Version: 2.4
Name: opengreywolfoptimizer
Version: 0.1.0
Summary: An async-compatible MPI-based Grey Wolf Optimizer
Author: Vaibhav Goll
Requires-Python: >=3.7
Requires-Dist: numpy
Requires-Dist: mpi4py
Dynamic: author
Dynamic: requires-dist
Dynamic: requires-python
Dynamic: summary
